planner
setup.cfg
setup.py
Agora_Planner.egg-info/PKG-INFO
Agora_Planner.egg-info/SOURCES.txt
Agora_Planner.egg-info/dependency_links.txt
Agora_Planner.egg-info/namespace_packages.txt
Agora_Planner.egg-info/requires.txt
Agora_Planner.egg-info/top_level.txt
agora/__init__.py
agora/planner/__init__.py
agora/planner/api.py
agora/planner/metadata.json
agora/planner/plan/__init__.py
agora/planner/plan/agp.py
agora/planner/plan/fountain.py
agora/planner/plan/graph.py
agora/planner/server/__init__.py
agora/planner/server/config.py
agora/planner/server/static/arbor.js
agora/planner/server/static/eager.eot
agora/planner/server/static/eager.svg
agora/planner/server/static/eager.ttf
agora/planner/server/static/eager.woff
agora/planner/server/static/graph.js
agora/planner/server/static/logo-sdh.png
agora/planner/server/static/paper.jpg
agora/planner/server/static/post-it.png
agora/planner/server/static/style.css
agora/planner/server/templates/graph.html
agora/planner/tests/__init__.py
agora/planner/tests/bad_gp_format_test.py
agora/planner/tests/empty_gp_test.py
agora/planner/tests/no_gp_test.py