Metadata-Version: 1.1
Name: Agora-Planner
Version: 0.3.7
Summary: The Agora core service that provides search plans for graph patterns
Home-page: https://github.com/smartdeveloperhub/agora-planner
Author: Fernando Serena
Author-email: fernando.serena@centeropenmiddleware.com
License: Apache 2
Download-URL: https://github.com/smartdeveloperhub/agora-planner/tarball/0.3.5-alpha1
Keywords: linked-data,path,ontology,plan
Platform: UNKNOWN
